<annotation>
	<folder>Gommose</folder>
	<filename>R_6_34-27-83-90_OP4_21PhotoEtatsante___3.jpg</filename>
	<path>D:\Nuisible_anacardier\ETAT_SANTE\Gommose\R_6_34-27-83-90_OP4_21PhotoEtatsante___3.jpg</path>
	<source>
		<database>Unknown</database>
	</source>
	<size>
		<width>768</width>
		<height>1024</height>
		<depth>3</depth>
	</size>
	<segmented>0</segmented>
	<object>
		<name>Gommose</name>
		<pose>Unspecified</pose>
		<truncated>0</truncated>
		<difficult>0</difficult>
		<bndbox>
			<xmin>132</xmin>
			<ymin>180</ymin>
			<xmax>449</xmax>
			<ymax>663</ymax>
		</bndbox>
	</object>
	<object>
		<name>Gommose</name>
		<pose>Unspecified</pose>
		<truncated>0</truncated>
		<difficult>0</difficult>
		<bndbox>
			<xmin>519</xmin>
			<ymin>588</ymin>
			<xmax>711</xmax>
			<ymax>885</ymax>
		</bndbox>
	</object>
</annotation>
