<annotation>
	<folder>Gommose</folder>
	<filename>R_12_92-64-15-90_OP4_21PhotoEtatsante___2.jpg</filename>
	<path>D:\Nuisible_anacardier\ETAT_SANTE\Gommose\R_12_92-64-15-90_OP4_21PhotoEtatsante___2.jpg</path>
	<source>
		<database>Unknown</database>
	</source>
	<size>
		<width>2448</width>
		<height>3264</height>
		<depth>3</depth>
	</size>
	<segmented>0</segmented>
	<object>
		<name>Gommose</name>
		<pose>Unspecified</pose>
		<truncated>1</truncated>
		<difficult>0</difficult>
		<bndbox>
			<xmin>744</xmin>
			<ymin>1</ymin>
			<xmax>1724</xmax>
			<ymax>3095</ymax>
		</bndbox>
	</object>
	<object>
		<name>Gommose</name>
		<pose>Unspecified</pose>
		<truncated>0</truncated>
		<difficult>0</difficult>
		<bndbox>
			<xmin>169</xmin>
			<ymin>2167</ymin>
			<xmax>689</xmax>
			<ymax>2482</ymax>
		</bndbox>
	</object>
</annotation>
