<annotation>
	<folder>Oïdium</folder>
	<filename>R_8_86-44-31-17_OP4_19PhotoEtatSante__.jpg</filename>
	<path>C:\Users\KOFFI OI\Desktop\MAX\NAYO\ETAT_SANTE\Oïdium\R_8_86-44-31-17_OP4_19PhotoEtatSante__.jpg</path>
	<source>
		<database>Unknown</database>
	</source>
	<size>
		<width>768</width>
		<height>1023</height>
		<depth>3</depth>
	</size>
	<segmented>0</segmented>
	<object>
		<name>Oidium</name>
		<pose>Unspecified</pose>
		<truncated>1</truncated>
		<difficult>0</difficult>
		<bndbox>
			<xmin>1</xmin>
			<ymin>627</ymin>
			<xmax>363</xmax>
			<ymax>1014</ymax>
		</bndbox>
	</object>
	<object>
		<name>Oidium</name>
		<pose>Unspecified</pose>
		<truncated>0</truncated>
		<difficult>0</difficult>
		<bndbox>
			<xmin>330</xmin>
			<ymin>582</ymin>
			<xmax>682</xmax>
			<ymax>928</ymax>
		</bndbox>
	</object>
</annotation>