<annotation>
	<folder>Termites</folder>
	<filename>R_17_04-90-77-88_OP4_21PhotoEtatsante___4.jpg</filename>
	<path>D:\Nuisible_anacardier\ETAT_SANTE\Termites\R_17_04-90-77-88_OP4_21PhotoEtatsante___4.jpg</path>
	<source>
		<database>Unknown</database>
	</source>
	<size>
		<width>2448</width>
		<height>3264</height>
		<depth>3</depth>
	</size>
	<segmented>0</segmented>
	<object>
		<name>Termites</name>
		<pose>Unspecified</pose>
		<truncated>0</truncated>
		<difficult>0</difficult>
		<bndbox>
			<xmin>974</xmin>
			<ymin>877</ymin>
			<xmax>1649</xmax>
			<ymax>1642</ymax>
		</bndbox>
	</object>
	<object>
		<name>Termites</name>
		<pose>Unspecified</pose>
		<truncated>0</truncated>
		<difficult>0</difficult>
		<bndbox>
			<xmin>1814</xmin>
			<ymin>1417</ymin>
			<xmax>1989</xmax>
			<ymax>1762</ymax>
		</bndbox>
	</object>
</annotation>
