<annotation>
	<folder>Termites</folder>
	<filename>R_19_56-20-77-74_OP4_15PhotoEltParcel__.jpg</filename>
	<path>D:\Nuisible_anacardier\ETAT_SANTE\Termites\R_19_56-20-77-74_OP4_15PhotoEltParcel__.jpg</path>
	<source>
		<database>Unknown</database>
	</source>
	<size>
		<width>2448</width>
		<height>3264</height>
		<depth>3</depth>
	</size>
	<segmented>0</segmented>
	<object>
		<name>Termites</name>
		<pose>Unspecified</pose>
		<truncated>0</truncated>
		<difficult>0</difficult>
		<bndbox>
			<xmin>224</xmin>
			<ymin>2057</ymin>
			<xmax>1744</xmax>
			<ymax>3257</ymax>
		</bndbox>
	</object>
	<object>
		<name>Termites</name>
		<pose>Unspecified</pose>
		<truncated>0</truncated>
		<difficult>0</difficult>
		<bndbox>
			<xmin>629</xmin>
			<ymin>982</ymin>
			<xmax>1134</xmax>
			<ymax>2032</ymax>
		</bndbox>
	</object>
</annotation>
