<annotation>
	<folder>Termites</folder>
	<filename>R_1_93-23-21-22_OP4_21PhotoEtatsante___1.jpg</filename>
	<path>D:\Nuisible_anacardier\ETAT_SANTE\Termites\R_1_93-23-21-22_OP4_21PhotoEtatsante___1.jpg</path>
	<source>
		<database>Unknown</database>
	</source>
	<size>
		<width>2448</width>
		<height>3264</height>
		<depth>3</depth>
	</size>
	<segmented>0</segmented>
	<object>
		<name>Termites</name>
		<pose>Unspecified</pose>
		<truncated>0</truncated>
		<difficult>0</difficult>
		<bndbox>
			<xmin>659</xmin>
			<ymin>37</ymin>
			<xmax>1189</xmax>
			<ymax>1732</ymax>
		</bndbox>
	</object>
</annotation>
