<annotation>
	<folder>Gommose</folder>
	<filename>R_20_94-94-50-98_OP4_21PhotoEtatsante___5.jpg</filename>
	<path>D:\Nuisible_anacardier\ETAT_SANTE\Gommose\R_20_94-94-50-98_OP4_21PhotoEtatsante___5.jpg</path>
	<source>
		<database>Unknown</database>
	</source>
	<size>
		<width>768</width>
		<height>1024</height>
		<depth>3</depth>
	</size>
	<segmented>0</segmented>
	<object>
		<name>Gommose</name>
		<pose>Unspecified</pose>
		<truncated>0</truncated>
		<difficult>0</difficult>
		<bndbox>
			<xmin>193</xmin>
			<ymin>353</ymin>
			<xmax>499</xmax>
			<ymax>719</ymax>
		</bndbox>
	</object>
</annotation>
