<annotation>
	<folder>Dysdercus wolkerii</folder>
	<filename>R_8_04-55-07-90_OP4_21PhotoEtatsante___1.jpg</filename>
	<path>C:\Users\KOFFI OI\Desktop\MAX\NAYO\ETAT_SANTE\Dysdercus wolkerii\R_8_04-55-07-90_OP4_21PhotoEtatsante___1.jpg</path>
	<source>
		<database>Unknown</database>
	</source>
	<size>
		<width>768</width>
		<height>1023</height>
		<depth>3</depth>
	</size>
	<segmented>0</segmented>
	<object>
		<name>Dysdercus wolkerii</name>
		<pose>Unspecified</pose>
		<truncated>0</truncated>
		<difficult>0</difficult>
		<bndbox>
			<xmin>165</xmin>
			<ymin>66</ymin>
			<xmax>385</xmax>
			<ymax>403</ymax>
		</bndbox>
	</object>
</annotation>