<annotation>
	<folder>Bactériose</folder>
	<filename>R_15_57-00-05-17_OP4_21PhotoEtatsante___5.jpg</filename>
	<path>D:\Nuisible_anacardier\ETAT_SANTE\Bactériose\R_15_57-00-05-17_OP4_21PhotoEtatsante___5.jpg</path>
	<source>
		<database>Unknown</database>
	</source>
	<size>
		<width>2448</width>
		<height>3264</height>
		<depth>3</depth>
	</size>
	<segmented>0</segmented>
	<object>
		<name>Bactériose</name>
		<pose>Unspecified</pose>
		<truncated>0</truncated>
		<difficult>0</difficult>
		<bndbox>
			<xmin>354</xmin>
			<ymin>767</ymin>
			<xmax>939</xmax>
			<ymax>1617</ymax>
		</bndbox>
	</object>
</annotation>
